{
  "categories": [
    {
      "id": 1000,
      "name": "State",
      "parent_id": null
    },
    {
      "id": 1001,
      "name": "NSW",
      "parent_id": 131
    },
    {
      "id": 1002,
      "name": "VIC",
      "parent_id": 131
    },
    {
      "id": 1003,
      "name": "QLD",
      "parent_id": 131
    },
    {
      "id": 1004,
      "name": "WA",
      "parent_id": 131
    },
    {
      "id": 1005,
      "name": "ACT",
      "parent_id": 131
    },
    {
      "id": 1006,
      "name": "National",
      "parent_id": null
    },
    {
      "id": 1007,
      "name": "World",
      "parent_id": null
    },
    {
      "id": 1008,
      "name": "Nation",
      "parent_id": 131
    },
    {
      "id": 1009,
      "name": "Worlds",
      "parent_id": null
    },
    {
      "id": 1010,
      "name": "Nation1",
      "parent_id": 131
    },
    {
      "id": 1011,
      "name": "Worlds1",
      "parent_id": 131
    },
    {
      "id": 1012,
      "name": "Nation2",
      "parent_id": 131
    },
    {
      "id": 1013,
      "name": "Worlds2",
      "parent_id": null
    },
    {
      "id": 1014,
      "name": "Nation3",
      "parent_id": 131
    },
    {
      "id": 1015,
      "name": "Worlds3",
      "parent_id": null
    },
    {
      "id": 1016,
      "name": "Nation4",
      "parent_id": 131
    },
    {
      "id": 1017,
      "name": "Worlds4",
      "parent_id": null
    },
    {
      "id": 1018,
      "name": "Nation5",
      "parent_id": 131
    },
    {
      "id": 1019,
      "name": "Worlds5",
      "parent_id": null
    }
  ]
}